mongodb_query_builder/__init__.py
mongodb_query_builder/__version__.py
mongodb_query_builder/exceptions.py
mongodb_query_builder/builders/__init__.py
mongodb_query_builder/builders/aggregate_builder.py
mongodb_query_builder/builders/atlas_search_builder.py
mongodb_query_builder/builders/query_filter.py
mongodb_query_builder/operators/__init__.py
mongodb_query_builder/operators/operators.py
mongodb_query_builder/utils/__init__.py
mongodb_query_builder/utils/type_helpers.py
mongodb_query_builder/utils/validation.py
mongodb_query_builder-1.0.1.dist-info/licenses/LICENSE
mongodb_query_builder-1.0.1.dist-info/METADATA
mongodb_query_builder-1.0.1.dist-info/WHEEL
mongodb_query_builder-1.0.1.dist-info/top_level.txt
mongodb_query_builder-1.0.1.dist-info/RECORD
