Metadata-Version: 2.4
Name: mongodb-query-builder
Version: 1.0.1
Summary: A fluent, type-safe query builder for MongoDB with support for aggregations and Atlas Search
Author-email: Christian De Asis <cdeasis923@gmail.comm>
Maintainer-email: Christian De Asis <cdeasis923@gmail.comm>
License: MIT
Project-URL: Homepage, https://github.com/ch-dev401/mongodb-query-builder
Project-URL: Documentation, https://mongodb-query-builder.readthedocs.io
Project-URL: Repository, https://github.com/ch-dev401/mongodb-query-builder
Project-URL: Bug Tracker, https://github.com/ch-dev401/mongodb-query-builder/issues
Project-URL: Changelog, https://github.com/ch-dev401/mongodb-query-builder/blob/main/CHANGELOG.md
Keywords: mongodb,query-builder,aggregation,atlas-search,database,fluent-api
Classifier: Development Status :: 4 - Beta
Classifier: Intended Audience :: Developers
Classifier: License :: OSI Approved :: MIT License
Classifier: Operating System :: OS Independent
Classifier: Programming Language :: Python :: 3
Classifier: Programming Language :: Python :: 3.8
Classifier: Programming Language :: Python :: 3.9
Classifier: Programming Language :: Python :: 3.10
Classifier: Programming Language :: Python :: 3.11
Classifier: Programming Language :: Python :: 3.12
Classifier: Topic :: Database
Classifier: Topic :: Software Development :: Libraries :: Python Modules
Classifier: Typing :: Typed
Requires-Python: >=3.8
License-File: LICENSE
Provides-Extra: mongodb
Requires-Dist: pymongo>=4.0.0; extra == "mongodb"
Provides-Extra: async
Requires-Dist: motor>=3.0.0; extra == "async"
Provides-Extra: dev
Requires-Dist: black>=25.9.0; extra == "dev"
Requires-Dist: flake8>=7.3.0; extra == "dev"
Requires-Dist: isort>=6.1.0; extra == "dev"
Requires-Dist: mypy>=1.18.2; extra == "dev"
Requires-Dist: pre-commit>=4.3.0; extra == "dev"
Requires-Dist: pylint>=3.3.8; extra == "dev"
Provides-Extra: test
Requires-Dist: pytest>=7.0.0; extra == "test"
Requires-Dist: pytest-cov>=4.0.0; extra == "test"
Requires-Dist: pytest-asyncio>=0.21.0; extra == "test"
Requires-Dist: mongomock>=4.1.0; extra == "test"
Provides-Extra: docs
Provides-Extra: all
Requires-Dist: mongodb-query-builder[async,dev,docs,mongodb,test]; extra == "all"
Dynamic: license-file
